{
  "version": "2.3.5",
  "flags": {},
  "shapes": [
    {
      "label": "bullet display",
      "points": [
        [
          1013.3170731707318,
          247.82926829268294
        ],
        [
          1357.560975609756,
          247.82926829268294
        ],
        [
          1357.560975609756,
          342.9512195121951
        ],
        [
          1013.3170731707318,
          342.9512195121951
        ]
      ],
      "group_id": 1,
      "description": "",
      "difficult": false,
      "shape_type": "rectangle",
      "flags": {},
      "attributes": {}
    },
    {
      "label": "1",
      "points": [
        [
          1031.1258278145694,
          272.8211920529801
        ]
      ],
      "group_id": 1,
      "description": "",
      "difficult": false,
      "shape_type": "point",
      "flags": {},
      "attributes": {}
    },
    {
      "label": "1",
      "points": [
        [
          1042.3841059602648,
          325.80132450331126
        ]
      ],
      "group_id": 1,
      "description": "",
      "difficult": false,
      "shape_type": "point",
      "flags": {},
      "attributes": {}
    },
    {
      "label": "1",
      "points": [
        [
          1334.4370860927152,
          314.5430463576159
        ]
      ],
      "group_id": 1,
      "description": "",
      "difficult": false,
      "shape_type": "point",
      "flags": {},
      "attributes": {}
    },
    {
      "label": "1",
      "points": [
        [
          1303.3112582781457,
          262.887417218543
        ]
      ],
      "group_id": 1,
      "description": "",
      "difficult": false,
      "shape_type": "point",
      "flags": {},
      "attributes": {}
    }
  ],
  "imagePath": "0000.jpg",
  "imageData": null,
  "imageHeight": 992,
  "imageWidth": 1920,
  "text": ""
}
